pdf_bookmark.py
pdf_bookmark-1.1.0.dist-info/LICENSE
pdf_bookmark-1.1.0.dist-info/METADATA
pdf_bookmark-1.1.0.dist-info/WHEEL
pdf_bookmark-1.1.0.dist-info/entry_points.txt
pdf_bookmark-1.1.0.dist-info/top_level.txt
pdf_bookmark-1.1.0.dist-info/RECORD
