Metadata-Version: 2.1
Name: pdf-bookmark
Version: 1.1.0
Summary: PDF Bookmark Import and Export
Home-page: https://github.com/xianghuzhao/pdf-bookmark
Author: Xianghu Zhao
Author-email: xianghuzhao@gmail.com
License: MIT
Platform: UNKNOWN
